LICENSE
pyproject.toml
readme.md
setup.cfg
setup.py
nppy/__init__.py
nppy.egg-info/PKG-INFO
nppy.egg-info/SOURCES.txt
nppy.egg-info/dependency_links.txt
nppy.egg-info/entry_points.txt
nppy.egg-info/requires.txt
nppy.egg-info/top_level.txt
nppy/dataset/__init__.py
nppy/dataset/mri_dataset_affine.py
nppy/inference/__init__.py
nppy/inference/nppy_inference.py
nppy/models/__init__.py
nppy/models/losses.py
nppy/models/model.py
nppy/models/utils.py
nppy/train/__init__.py
nppy/train/train.py