Metadata-Version: 2.1
Name: nppy
Version: 0.2.1
Summary: Neural Pre-Processing: A Learning Framework for End-to-end Brain MRI Pre-processing.
Author-email: Xinzi He <xh278@cornell.edu>
License:                                  Apache License
Project-URL: homepage, https://github.com/Novestars
Project-URL: repository, https://github.com/Novestars/Neural_Pre_Processing
Keywords: deep learning,brain MRI,MRI preprocessing,neural pre-processing,nppy
Classifier: Development Status :: 4 - Beta
Classifier: Intended Audience :: Developers
Classifier: Intended Audience :: Science/Research
Classifier: Intended Audience :: Healthcare Industry
Classifier: Programming Language :: Python :: 3
Classifier: License :: OSI Approved :: Apache Software License
Classifier: Topic :: Scientific/Engineering :: Artificial Intelligence
Classifier: Topic :: Scientific/Engineering :: Image Recognition
Classifier: Topic :: Scientific/Engineering :: Medical Science Apps.
Requires-Python: >=3.7
License-File: LICENSE
